Metadata-Version: 1.0
Name: Raj-9100
Version: 1.1
Summary: Gaussian distributions
Home-page: UNKNOWN
Author: GaneshRaj
Author-email: edugan28@gmail.com
License: UNKNOWN
Platform: UNKNOWN
